Metadata-Version: 2.1
Name: training-dashboard
Version: 0.1.0
Summary: No bullshit, dead simple training visualizer for tf-keras.
Home-page: https://github.com/vibhuagrawal14/training_dashboard
Author: Vibhu Agrawal
Author-email: vibhu.agrawal14@gmail.com
License: MIT
Platform: UNKNOWN
Classifier: License :: OSI Approved :: MIT License
Classifier: Programming Language :: Python
Classifier: Programming Language :: Python :: 3
Classifier: Programming Language :: Python :: Implementation :: CPython
Classifier: Programming Language :: Python :: Implementation :: PyPy
